Metadata-Version: 1.1
Name: fbads
Version: 0.3.5
Summary: Python client for the Facebook Ads API
Home-page: http://fbads.readthedocs.org/en/latest/
Author: Renato Pedigoni
Author-email: renatopedigoni@gmail.com
License: UNKNOWN
Keywords: facebook ads api
Platform: UNKNOWN
Classifier: Programming Language :: Python
Classifier: Topic :: Software Development :: Libraries :: Python Modules
